autqec/XY_dualities.py
autqec/ZX_dualities.py
autqec/ZY_dualities.py
autqec/__init__.py
autqec/algorithm_outline.png
autqec/automorphisms.py
autqec/code_embedding.py
autqec/graph_auts.py
autqec/logical_subgroups.py
autqec/magma_interface.py
autqec/py.typed
autqec/tests/__init__.py
autqec/tests/clifford_subgroup_membership.py
autqec/tests/test_ZX_dualities.py
autqec/tests/test_automorphisms.py
autqec/tests/test_clifford_subgroup_membership.py
autqec/tests/test_magma_interface.py
autqec/tests/test_symp_to_clifford.py
autqec/tests/test_utils/__init__.py
autqec/tests/test_utils/test_linalg.py
autqec/tests/test_utils/test_pauli.py
autqec/tests/test_utils/test_perms.py
autqec/tests/test_utils/test_qec.py
autqec/tests/test_utils/test_qiskit.py
autqec/tests/test_utils/test_symplectic.py
autqec/utils/__init__.py
autqec/utils/linalg.py
autqec/utils/magma.py
autqec/utils/pauli.py
autqec/utils/perms.py
autqec/utils/qec.py
autqec/utils/qiskit.py
autqec/utils/symplectic.py
autqec-1.0.1.dist-info/LICENSE
autqec-1.0.1.dist-info/METADATA
autqec-1.0.1.dist-info/WHEEL
autqec-1.0.1.dist-info/RECORD
