Metadata-Version: 2.1
Name: autqec
Version: 1.0.1
Summary: Tools for finding logical Clifford gates of QEC stabilizer codes from code automorphisms.
Home-page: https://github.com/hsayginel/autqec
License: GNU General Public License v3.0, 29 June 2007
Keywords: quantum computing,quantum error correction,quantum low-density parity check codes,LDPC
Author: Hasan Sayginel
Author-email: hasan.sayginel.17@ucl.ac.uk
Requires-Python: >=3.11
Classifier: Intended Audience :: Science/Research
Classifier: License :: OSI Approved :: GNU General Public License v3 (GPLv3)
Classifier: License :: Other/Proprietary License
Classifier: Natural Language :: English
Classifier: Operating System :: OS Independent
Classifier: Programming Language :: Python :: 3
Classifier: Programming Language :: Python :: 3.11
Classifier: Programming Language :: Python :: 3.12
Classifier: Programming Language :: Python :: 3.13
Classifier: Topic :: Scientific/Engineering :: Mathematics
Classifier: Topic :: Scientific/Engineering :: Physics
Requires-Dist: igraph (>=0.11.8)
Requires-Dist: matplotlib (>=3.9.1)
Requires-Dist: numba (>=0.60.0)
Requires-Dist: numpy (>=1.26.2)
Requires-Dist: pylatexenc (>=2.10)
Requires-Dist: pytest (>=8.3.1)
Requires-Dist: qiskit (>=1.1.1)
Project-URL: Repository, https://github.com/hsayginel/autqec
